[
    {
        "id": "2b13b1cdc2b60607",
        "type": "delay",
        "z": "e2af8452c5ac0d96",
        "name": "",
        "pauseType": "delay",
        "timeout": "5",
        "timeoutUnits": "seconds",
        "rate": "1",
        "nbRateUnits": "1",
        "rateUnits": "second",
        "randomFirst": "1",
        "randomLast": "5",
        "randomUnits": "seconds",
        "drop": false,
        "allowrate": false,
        "outputs": 1,
        "x": 980,
        "y": 540,
        "wires": [
            [
                "b24046d749a2389e"
            ]
        ]
    }
]